LICENSE
MANIFEST.in
README.rst
setup.py
py_instagram_dl/__init__.py
py_instagram_dl/core.py
py_instagram_dl/exceptions.py
py_instagram_dl.egg-info/PKG-INFO
py_instagram_dl.egg-info/SOURCES.txt
py_instagram_dl.egg-info/dependency_links.txt
py_instagram_dl.egg-info/top_level.txt