Metadata-Version: 1.1
Name: py-instagram-dl
Version: 1.4
Summary: A Python package to download all pictures from an Instagram user profile. 
Home-page: http://www.thepythondjango.com/
Author: Anurag Rana
Author-email: UNKNOWN
License: MIT License
Keywords: instagram dowloader,instagram scrapper,instagram picture downloads
Platform: UNKNOWN
Classifier: Development Status :: 5 - Production/Stable
Classifier: Environment :: Web Environment
Classifier: Intended Audience :: Developers
Classifier: License :: OSI Approved :: MIT License
Classifier: Operating System :: OS Independent
Classifier: Programming Language :: Python
Classifier: Programming Language :: Python :: 3.4
Classifier: Programming Language :: Python :: 3.5
Classifier: Programming Language :: Python :: 3.6
Classifier: Topic :: Internet :: WWW/HTTP
Classifier: Topic :: Internet :: WWW/HTTP :: Dynamic Content
